{
	"name": "CoinFlip",
	"plugin-id": "Sprite",
	"sid": 795156998790036,
	"isGlobal": false,
	"editorNewInstanceIsReplica": true,
	"instanceVariables": [],
	"behaviorTypes": [],
	"effectTypes": [],
	"animations": {
		"items": [
			{
				"frames": [
					{
						"width": 300,
						"height": 301,
						"originX": 0.5,
						"originY": 0.5,
						"originalSource": "",
						"exportFormat": "lossless",
						"exportQuality": 0.8,
						"fileType": "image/png",
						"imageSpriteId": 4327126,
						"collisionPoly": {
							"points": [
								0.44666666666666666,
								0.006644518272425249,
								0.5566666666666666,
								0.006644518272425249,
								0.9533333333333334,
								0.29900332225913623,
								0.9933333333333333,
								0.46511627906976744,
								0.9933333333333333,
								0.5614617940199336,
								0.9766666666666667,
								0.6445182724252492,
								0.8666666666666667,
								0.8372093023255814,
								0.7766666666666666,
								0.9136212624584718,
								0.5566666666666666,
								0.9933554817275747,
								0.44666666666666666,
								0.9933554817275747,
								0.013333333333333334,
								0.5548172757475083,
								0.013333333333333334,
								0.44518272425249167
							]
						},
						"useCollisionPoly": true,
						"duration": 1,
						"tag": ""
					},
					{
						"width": 298,
						"height": 301,
						"originX": 0.5,
						"originY": 0.5,
						"originalSource": "",
						"exportFormat": "lossless",
						"exportQuality": 0.8,
						"fileType": "image/png",
						"imageSpriteId": 4474772,
						"collisionPoly": {
							"points": [
								0.44966442953020136,
								0.006644518272425249,
								0.5604026845637584,
								0.006644518272425249,
								0.959731543624161,
								0.29900332225913623,
								1,
								0.46511627906976744,
								1,
								0.5614617940199336,
								0.9832214765100671,
								0.6445182724252492,
								0.87248322147651,
								0.8372093023255814,
								0.7818791946308725,
								0.9136212624584718,
								0.5604026845637584,
								0.9933554817275747,
								0.44966442953020136,
								0.9933554817275747,
								0.013422818791946308,
								0.5548172757475083,
								0.013422818791946308,
								0.44518272425249167
							]
						},
						"useCollisionPoly": true,
						"duration": 1,
						"tag": ""
					}
				],
				"sid": 465568148305935,
				"name": "Animation 1",
				"isLooping": true,
				"isPingPong": false,
				"repeatCount": 1,
				"repeatTo": 0,
				"speed": 0
			}
		],
		"subfolders": []
	}
}